classes/__init__.py
classes/bip.py
classes/uc.py
functions/__init__.py
functions/banner.py
functions/clear.py
functions/csf.py
functions/req.py
functions/sto.py
process/__init__.py
process/core.py
wikilyzer_ska_1-0.0.0.dist-info/LICENSE
wikilyzer_ska_1-0.0.0.dist-info/METADATA
wikilyzer_ska_1-0.0.0.dist-info/WHEEL
wikilyzer_ska_1-0.0.0.dist-info/entry_points.txt
wikilyzer_ska_1-0.0.0.dist-info/top_level.txt
wikilyzer_ska_1-0.0.0.dist-info/RECORD
