Metadata-Version: 2.1
Name: wikilyzer-ska-1
Version: 0.0.0
Summary: analyzer for wikipedia
Home-page: https://github.com/ska-arsam-kazempour/wikilyzer
Author: Arsam Kazempour
Author-email: ska.arsam.kazempour@gmail.com
License: MIT
Platform: UNKNOWN
License-File: LICENSE
